ostristraining/__init__.py
ostristraining/config_utils.py
ostristraining/dataset_utils.py
ostristraining/example.py
ostristraining/example_config.yaml
ostristraining/main.py
techtrash_ostristraining-0.1.3.dist-info/METADATA
techtrash_ostristraining-0.1.3.dist-info/WHEEL
techtrash_ostristraining-0.1.3.dist-info/licenses/LICENSE
techtrash_ostristraining-0.1.3.dist-info/RECORD
