Metadata-Version: 2.4
Name: TechTrash_OstrisTraining
Version: 0.1.3
Summary: A package to use the OstrisTraining
Author-email: Clapin Arthur <clapin.arthur@gmail.com>
License-Expression: MIT
License-File: LICENSE
Classifier: Operating System :: OS Independent
Classifier: Programming Language :: Python :: 3
Requires-Python: >=3.10
Requires-Dist: asyncio==4.0.0
Requires-Dist: nvidia-ml-py==13.580.82
Requires-Dist: pynvml==13.0.1
Requires-Dist: pyyaml==6.0.2
Requires-Dist: requests==2.32.3
